synthesizer/__main__.py
synthesizer/parser.py
synthesizer/pipeline.py
synthesizer/utils.py
synthesizer/dustmixer/__init__.py
synthesizer/dustmixer/bhcoat.py
synthesizer/dustmixer/bhmie.py
synthesizer/dustmixer/dustmixer.py
synthesizer/examples/disk_zoo_api.py
synthesizer/examples/dust_mixing_api.py
synthesizer/examples/ppdisk_synobs_api.py
synthesizer/gridder/__init__.py
synthesizer/gridder/analytical.py
synthesizer/gridder/custom_model.py
synthesizer/gridder/gridder.py
synthesizer/gridder/hydro_reader.py
synthesizer/gridder/models.py
synthesizer/gridder/vector_field.py
synthesizer/raytrace/__init__.py
synthesizer/raytrace/radmc3d.py
synthesizer/synobs/__init__.py
synthesizer/synobs/scripter.py
synthesizer/synobs/syn_imager.py
synthesizer/synobs/templates/alma_1.3mm.py
synthesizer/synobs/templates/alma_1.3mm_pol.py
synthesizer/synobs/templates/alma_3mm.py
synthesizer/synobs/templates/vla_18mm.py
synthesizer/synobs/templates/vla_7mm.py
synthesizer/synobs/templates/vla_9mm.py
astro_synthesizer-1.0.2.dist-info/LICENSE
astro_synthesizer-1.0.2.dist-info/METADATA
astro_synthesizer-1.0.2.dist-info/WHEEL
astro_synthesizer-1.0.2.dist-info/entry_points.txt
astro_synthesizer-1.0.2.dist-info/top_level.txt
astro_synthesizer-1.0.2.dist-info/RECORD
