Metadata-Version: 2.1
Name: astro-synthesizer
Version: 1.0.2
Summary: Generate astronomical synthetic observations from the command-line 
Author-email: Joaquin Zamponi <jzamponi@mpe.mpg.de>
License: GNU GENERAL PUBLIC LICENSE
Project-URL: Homepage, https://github.com/jzamponi/synthesizer
Keywords: ,,
Classifier: License :: OSI Approved :: MIT License
Classifier: Programming Language :: Python
Classifier: Programming Language :: Python :: 3
Requires-Python: >=3.10
License-File: LICENSE
Requires-Dist: requests
Requires-Dist: astropy >=5.1
Requires-Dist: matplotlib
Requires-Dist: numpy
Requires-Dist: scipy
Requires-Dist: mpmath
Requires-Dist: progressbar2
Requires-Dist: aplpy
Requires-Dist: h5py
Requires-Dist: yt
Requires-Dist: pyqt5
Requires-Dist: mayavi
